{"is_source_file": false, "format": "", "description": "", "external_files": [], "external_methods": [], "published": [], "classes": [], "methods": [], "calls": [], "search-terms": [], "state": 2, "file_id": 1, "knowledge_revision": 6, "git_revision": "ed6fdc83d5bdfb0599191f9175cea4bf3f61ff3d", "hash": "67bb45472972bcac6c56e5d9a133a942", "format-version": 4, "code-base-name": "travel_planner_backend", "filename": "README.md", "revision_history": [{"6": "ed6fdc83d5bdfb0599191f9175cea4bf3f61ff3d"}]}